{
    "id": "19-187_s1_p5",
    "series": {
        "id": "19-187",
        "title": "メタリックルージュ",
        "label": {},
        "thumbComponent": {
            "urlPrefix": "https://image.p-c2-x.abema-tv.com/image/series/19-187",
            "filename": "thumb.png",
            "query": "version=1703493799",
            "extension": "png"
        },
        "thumbPortraitComponent": {
            "urlPrefix": "https://image.p-c2-x.abema-tv.com/image/series/19-187",
            "filename": "portrait.png",
            "query": "version=1703493799",
            "extension": "png"
        }
    },
    "season": {
        "id": "19-187_s1",
        "sequence": 1,
        "name": "シーズン1",
        "thumbComponent": {},
        "order": 1
    },
    "genre": {
        "id": "animation",
        "name": "アニメ",
        "subGenres": [
            {
                "id": "animation_41",
                "name": "Abemaアニメ"
            },
            {
                "id": "animation_2",
                "name": "アクション・バトル"
            }
        ]
    },
    "info": {
        "duration": 1369
    },
    "providedInfo": {
        "thumbImg": "thumb001",
        "sceneThumbImgs": [
            "thumb002",
            "thumb003",
            "thumb004",
            "thumb005",
            "thumb006"
        ]
    },
    "episode": {
        "number": 5,
        "title": "第5話 カーニバルは忘却と踊る",
        "content": "ネアン居留地でリオンの死体を見つけるナオミ。しかし、そこにルジュの姿はない。そんなナオミの前に現れる一人の人物。それは以前、簒奪者の遺跡を探っていた謎の男性であった。彼はルジュの居場所を知っており、そこへナオミを案内すると言う。一方、捕らわれのルジュは夢とも記憶ともつかない幻の中をさまよっていた。生まれたばかりの自分。優しく温かかった兄『ジーン・ユングハルト』、父『ロイ・ユングハルト』との日々。そして見知らぬ女性と仮面の男。同じ頃、男と共にある場所にやって来たナオミ。そこは移動カーニバル。ルジュはこの中にいると言う男、『エデン・ヴァロック』と名乗る彼と共に、ナオミは移動カーニバルへと潜入して行く。"
    },
    "credit": {
        "released": 2024,
        "casts": [
            "ルジュ・レッドスター：宮本侑芽",
            "ナオミ・オルトマン：黒沢ともよ",
            "ジーン・ユングハルト：武内駿輔"
        ],
        "crews": [
            "総監修：出渕 裕",
            "シリーズ構成：出渕 裕　根元歳三",
            "監督：堀 元宣",
            "キャラクターデザイン：川元利浩",
            "特技監督：村木 靖",
            "グラディエーターデザイン：竹谷隆之・篠原 保",
            "メカニカルデザイン：平尾朋之",
            "プロダクトデザイン：宮武一貴",
            "セットデザイン：武半慎吾・石津泰志",
            "コスチュームデザイン協力：山田章博",
            "美術監督：海老澤卓也",
            "色彩設計：梅崎ひろこ",
            "撮影監督：池上真崇",
            "3DCGスーパーバイザー：今 義和",
            "3DCGディレクター：内田大樹",
            "設定考証：堺 三保",
            "文化考証：柴田勝家",
            "音響監督：山田 陽"
        ],
        "copyrights": [
            "(C)BONES・出渕裕／Project Rouge"
        ]
    },
    "mediaStatus": {},
    "label": {},
    "imageUpdatedAt": 1712655674,
    "endAt": 1748703600,
    "transcodeVersion": "tRZY4",
    "sharedLink": {
        "twitter": "https://abema.app/MU3T",
        "facebook": "https://abema.app/Bima",
        "google": "https://abema.app/h73R",
        "line": "https://abema.app/yMnd",
        "copy": "https://abema.app/LJmy",
        "instagram": "https://abema.app/bZkY"
    },
    "playback": {
        "hls": "https://ds-vod-abematv.akamaized.net/program/19-187_s1_p5/playlist.m3u8",
        "dash": "https://ds-vod-abematv.akamaized.net/program/19-187_s1_p5/manifest.mpd",
        "dashIPTV": "https://ds-vod-abematv.akamaized.net/program/19-187_s1_p5/manifest.mpd",
        "arin": "abm1.legacy-playout.program.19-187_s1_p5"
    },
    "viewingPoint": {
        "suggestion": 1280.2372916666666,
        "opening": {
            "start": 96.01258333333334,
            "end": 185.93575
        },
        "ending": {
            "start": 1280.2372916666666,
            "end": 1369.9102083333332
        }
    },
    "nextProgramInfo": {
        "programId": "19-187_s1_p6",
        "title": "第6話 名前がない客",
        "thumbImg": "thumb001",
        "sceneThumbImages": [
            "thumb002",
            "thumb003",
            "thumb004",
            "thumb005",
            "thumb006"
        ],
        "imageUpdatedAt": 1712655674,
        "endAt": 1748703600,
        "broadcastRegionPolicy": 1,
        "terms": [
            {
                "onDemandType": 1,
                "endAt": 1748703600
            }
        ]
    },
    "download": {
        "enable": true
    },
    "externalContent": {
        "marks": {}
    },
    "broadcastRegionPolicy": 1,
    "timelineThumbComponent": {
        "urlPrefix": "https://image.p-c2-x.abema-tv.com/media/programs/19-187_s1_p5/1/timeline",
        "extension": "png"
    },
    "terms": [
        {
            "onDemandType": 1,
            "endAt": 1748703600
        }
    ],
    "episodeGroupId": "19-187_eg0",
    "skipVmap": true
}