{
    "id": "25-55_s5_p57",
    "series": {
        "id": "25-55",
        "title": "文豪ストレイドッグス",
        "label": {
            "someFree": true
        },
        "thumbComponent": {
            "urlPrefix": "https://image.p-c2-x.abema-tv.com/image/series/25-55",
            "filename": "thumb.png",
            "query": "version=1687770075",
            "extension": "png"
        },
        "thumbPortraitComponent": {
            "urlPrefix": "https://image.p-c2-x.abema-tv.com/image/series/25-55",
            "filename": "portrait.png",
            "query": "version=1687770075",
            "extension": "png"
        }
    },
    "season": {
        "id": "25-55_s5",
        "sequence": 5,
        "name": "第5シーズン",
        "thumbComponent": {},
        "order": 2
    },
    "genre": {
        "id": "animation",
        "name": "アニメ",
        "subGenres": [
            {
                "id": "animation_2",
                "name": "アクション・バトル"
            },
            {
                "id": "animation_14",
                "name": "戦争・ミリタリー"
            },
            {
                "id": "animation_41",
                "name": "Abemaアニメ"
            }
        ]
    },
    "info": {
        "duration": 1420
    },
    "providedInfo": {
        "thumbImg": "thumb001",
        "sceneThumbImgs": [
            "thumb002",
            "thumb003",
            "thumb004",
            "thumb005",
            "thumb006"
        ]
    },
    "episode": {
        "number": 57,
        "title": "第57話 空ノ港ニテ（其の三）",
        "content": "ニコライが、シグマを連れてムルソーにあらわれた。30分で死に至る毒を打ち、先に脱獄した方が解毒剤を得るという決闘を受け入れる太宰とフョードル。ニコライは、地上の出口まで如何に世界最高峰の警備機構が待ち受けるかということを嬉々として説明し、用意した道具のうち１つを選んで持っていくように促す。だが、そこで、太宰が指差したものは……。その頃、ブラムが盗まれたことに気づいた福地は、空港中の吸血種に命じて犯人の捜索を行っていた。"
    },
    "credit": {
        "released": 2023,
        "casts": [
            "中島 敦：上村祐翔",
            "太宰 治：宮野真守",
            "国木田独歩：細谷佳正",
            "江戸川乱歩：神谷浩史",
            "谷崎潤一郎：豊永利行",
            "宮沢賢治：花倉桔道",
            "与謝野晶子：嶋村 侑",
            "泉 鏡花：諸星すみれ",
            "福沢諭吉：小山力也",
            "芥川龍之介：小野賢章",
            "中原中也：谷山紀章",
            "フョードル・D：石田 彰",
            "ニコライ・G：子安武人",
            "シグマ：千葉翔也",
            "条野採菊：梶 裕貴",
            "末広鉄腸：阿座上洋平",
            "立原道造：林 勇",
            "大倉燁子：小市眞琴",
            "福地桜痴：大塚明夫"
        ],
        "crews": [
            "原作：朝霧カフカ",
            "漫画：春河３５（「ヤングエース」連載）",
            "監督：五十嵐卓哉",
            "シリーズ構成・脚本：榎戸洋司",
            "キャラクターデザイン・総作画監督：新井伸浩",
            "プロップデザイン：片貝文洋",
            "美術監督：近藤由美子",
            "色彩設計：後藤ゆかり",
            "撮影監督：神林 剛",
            "3DCG監督：安東容太、小栗裕樹",
            "編集：西山 茂",
            "音楽：岩崎 琢",
            "音楽制作：ランティス",
            "音響監督：若林和弘",
            "音響効果：倉橋静男(サウンドボックス)、西佐知子(サウンドボックス)",
            "音響制作：グロービジョン",
            "オープニング主題歌アーティスト：GRANRODEO",
            "エンディング主題歌アーティスト：ラックライフ",
            "アニメーション制作：ボンズ",
            "製作：文豪ストレイドッグス製作委員会"
        ],
        "copyrights": [
            "(C)朝霧カフカ・春河35/ＫＡＤＯＫＡＷＡ/文豪ストレイドッグス製作委員会"
        ]
    },
    "mediaStatus": {},
    "label": {},
    "imageUpdatedAt": 1695891390,
    "endAt": 1727708400,
    "transcodeVersion": "2QhB8C",
    "sharedLink": {
        "twitter": "https://abema.app/LZxR",
        "facebook": "https://abema.app/eAkb",
        "google": "https://abema.app/xapp",
        "line": "https://abema.app/6zuU",
        "copy": "https://abema.app/z2F3",
        "instagram": "https://abema.app/Vdir"
    },
    "playback": {
        "hls": "https://ds-vod-abematv.akamaized.net/program/25-55_s5_p57/playlist.m3u8",
        "dash": "https://ds-vod-abematv.akamaized.net/program/25-55_s5_p57/manifest.mpd",
        "dashIPTV": "https://ds-vod-abematv.akamaized.net/program/25-55_s5_p57/manifest.mpd",
        "arin": "abm1.legacy-playout.program.25-55_s5_p57"
    },
    "viewingPoint": {
        "suggestion": 1332.1975333333332,
        "opening": {
            "start": 277.5773,
            "end": 366.59956666666665
        },
        "ending": {
            "start": 1332.1975333333332,
            "end": 1415.9812333333334
        }
    },
    "nextProgramInfo": {
        "programId": "25-55_s5_p58",
        "title": "第58話 人外魔境（其の一）",
        "thumbImg": "thumb001",
        "sceneThumbImages": [
            "thumb002",
            "thumb003",
            "thumb004",
            "thumb005",
            "thumb006"
        ],
        "imageUpdatedAt": 1695891390,
        "endAt": 1727708400,
        "broadcastRegionPolicy": 1,
        "terms": [
            {
                "onDemandType": 1,
                "endAt": 1727708400
            }
        ]
    },
    "download": {
        "enable": true
    },
    "externalContent": {
        "marks": {}
    },
    "broadcastRegionPolicy": 1,
    "timelineThumbComponent": {
        "urlPrefix": "https://image.p-c2-x.abema-tv.com/media/programs/25-55_s5_p57/1/timeline",
        "extension": "png"
    },
    "terms": [
        {
            "onDemandType": 1,
            "endAt": 1727708400
        }
    ],
    "episodeGroupId": "25-55_eg0"
}